[
  {
    "SmeltedOreId": "150",
    "Experience": "6",
    "BarId": "169",
    "RequiredLevel": "1",
    "RequiredOreId": "202",
    "RequiredOreAmount": "1"
  },
  {
    "SmeltedOreId": "202",
    "Experience": "6",
    "BarId": "169",
    "RequiredLevel": "1",
    "RequiredOreId": "150",
    "RequiredOreAmount": "1"
  },
  {
    "SmeltedOreId": "383",
    "Experience": "13",
    "BarId": "384",
    "RequiredLevel": "20"
  },
  {
    "SmeltedOreId": "151",
    "Experience": "17",
    "BarId": "171",
    "RequiredLevel": "30",
    "RequiredOreId": "155",
    "RequiredOreAmount": "2"
  },
  {
    "SmeltedOreId": "152",
    "Experience": "22",
    "BarId": "172",
    "RequiredLevel": "40"
  },
  {
    "SmeltedOreId": "153",
    "Experience": "30",
    "BarId": "173",
    "RequiredLevel": "50",
    "RequiredOreId": "155",
    "RequiredOreAmount": "4"
  },
  {
    "SmeltedOreId": "154",
    "Experience": "37",
    "BarId": "174",
    "RequiredLevel": "70",
    "RequiredOreId": "155",
    "RequiredOreAmount": "6"
  },
  {
    "SmeltedOreId": "409",
    "Experience": "50",
    "BarId": "408",
    "RequiredLevel": "85",
    "RequiredOreId": "155",
    "RequiredOreAmount": "8"
  }
]