{
  "map": {
    "entry": [
      {
        "int": "225",
        "CerterDef": {
          "type": "ore",
          "certs": {
            "CertDef": [
              {
                "name": "Iron",
                "certID": "517",
                "itemID": "151"
              },
              {
                "name": "Coal",
                "certID": "518",
                "itemID": "155"
              },
              {
                "name": "Mithril",
                "certID": "519",
                "itemID": "153"
              },
              {
                "name": "Adamantite",
                "certID": "1295",
                "itemID": "154"
              },
              {
                "name": "Gold",
                "certID": "521",
                "itemID": "152"
              },
              {
                "name": "Silver",
                "certID": "520",
                "itemID": "383"
              }
            ]
          }
        }
      },
      {
        "int": "226",
        "CerterDef": {
          "type": "bar",
          "certs": {
            "CertDef": [
              {
                "name": "Iron",
                "certID": "528",
                "itemID": "170"
              },
              {
                "name": "Steel",
                "certID": "529",
                "itemID": "171"
              },
              {
                "name": "Mithril",
                "certID": "530",
                "itemID": "173"
              },
              {
                "name": "Adamantite",
                "certID": "1296",
                "itemID": "174"
              },
              {
                "name": "Gold",
                "certID": "532",
                "itemID": "172"
              },
              {
                "name": "Silver",
                "certID": "531",
                "itemID": "384"
              }
            ]
          }
        }
      },
      {
        "int": "227",
        "CerterDef": {
          "type": "fish",
          "certs": {
            "CertDef": [
              {
                "name": "Trout",
                "certID": "1306",
                "itemID": "359"
              },
              {
                "name": "Raw Trout",
                "certID": "1305",
                "itemID": "358"
              },
              {
                "name": "Salmon",
                "certID": "1308",
                "itemID": "357"
              },
              {
                "name": "Raw Salmon",
                "certID": "1307",
                "itemID": "356"
              },
              {
                "name": "Lobster",
                "certID": "533",
                "itemID": "373"
              },
              {
                "name": "Raw Lobster",
                "certID": "534",
                "itemID": "372"
              },
              {
                "name": "Swordfish",
                "certID": "535",
                "itemID": "370"
              },
              {
                "name": "Raw Swordfish",
                "certID": "536",
                "itemID": "369"
              },
              {
                "name": "Tuna",
                "certID": "1291",
                "itemID": "367"
              },
              {
                "name": "Raw Tuna",
                "certID": "1292",
                "itemID": "366"
              }
            ]
          }
        }
      },
      {
        "int": "466",
        "CerterDef": {
          "type": "ore",
          "certs": {
            "CertDef": [
              {
                "name": "Iron",
                "certID": "517",
                "itemID": "151"
              },
              {
                "name": "Coal",
                "certID": "518",
                "itemID": "155"
              },
              {
                "name": "Mithril",
                "certID": "519",
                "itemID": "153"
              },
              {
                "name": "Adamantite",
                "certID": "1295",
                "itemID": "154"
              },
              {
                "name": "Gold",
                "certID": "521",
                "itemID": "152"
              },
              {
                "name": "Silver",
                "certID": "520",
                "itemID": "383"
              }
            ]
          }
        }
      },
      {
        "int": "467",
        "CerterDef": {
          "type": "bar",
          "certs": {
            "CertDef": [
              {
                "name": "Iron",
                "certID": "528",
                "itemID": "170"
              },
              {
                "name": "Steel",
                "certID": "529",
                "itemID": "171"
              },
              {
                "name": "Mithril",
                "certID": "530",
                "itemID": "173"
              },
              {
                "name": "Adamantite",
                "certID": "1296",
                "itemID": "174"
              },
              {
                "name": "Gold",
                "certID": "532",
                "itemID": "172"
              },
              {
                "name": "Silver",
                "certID": "531",
                "itemID": "384"
              }
            ]
          }
        }
      },
      {
        "int": "299",
        "CerterDef": {
          "type": "fish",
          "certs": {
            "CertDef": [
              {
                "name": "Shark",
                "certID": "630",
                "itemID": "546"
              },
              {
                "name": "Raw Shark",
                "certID": "631",
                "itemID": "545"
              },
              {
                "name": "Bass",
                "certID": "628",
                "itemID": "555"
              },
              {
                "name": "Raw Bass",
                "certID": "629",
                "itemID": "554"
              }
            ]
          }
        }
      },
      {
        "int": "778",
        "CerterDef": {
          "type": "potion",
          "certs": {
            "CertDef": [
              {
                "name": "Attack Potion",
                "certID": "1302",
                "itemID": "474"
              },
              {
                "name": "Strength Potion",
                "certID": "1304",
                "itemID": "222"
              },
              {
                "name": "Defense Potion",
                "certID": "1303",
                "itemID": "480"
              },
              {
                "name": "Super Attack Potion",
                "certID": "1273",
                "itemID": "486"
              },
              {
                "name": "Super Defense Potion",
                "certID": "1274",
                "itemID": "495"
              },
              {
                "name": "Super Strength Potion",
                "certID": "1275",
                "itemID": "492"
              },
              {
                "name": "Prayer Potion",
                "certID": "1272",
                "itemID": "483"
              },
              {
                "name": "Ranged Potion",
                "certID": "1301",
                "itemID": "498"
              }
            ]
          }
        }
      },
      {
        "int": "347",
        "CerterDef": {
          "type": "bone",
          "certs": {
            "CertDef": [
              {
                "name": "Big Bones",
                "certID": "1300",
                "itemID": "413"
              },
              {
                "name": "Dragon Bones",
                "certID": "1270",
                "itemID": "814"
              }
            ]
          }
        }
      },
      {
        "int": "341",
        "CerterDef": {
          "type": "log",
          "certs": {
            "CertDef": [
              {
                "name": "Magic Logs",
                "certID": "1310",
                "itemID": "636"
              },
              {
                "name": "Yew Logs",
                "certID": "711",
                "itemID": "635"
              },
              {
                "name": "Maple Logs",
                "certID": "712",
                "itemID": "634"
              },
              {
                "name": "Willow Logs",
                "certID": "713",
                "itemID": "633"
              },
              {
                "name": "Oak Logs",
                "certID": "1290",
                "itemID": "632"
              }
            ]
          }
        }
      },
      {
        "int": "348",
        "CerterDef": {
          "type": "log",
          "certs": {
            "CertDef": [
              {
                "name": "Magic Logs",
                "certID": "1310",
                "itemID": "636"
              },
              {
                "name": "Yew Logs",
                "certID": "711",
                "itemID": "635"
              },
              {
                "name": "Maple Logs",
                "certID": "712",
                "itemID": "634"
              },
              {
                "name": "Willow Logs",
                "certID": "713",
                "itemID": "633"
              },
              {
                "name": "Oak Logs",
                "certID": "1290",
                "itemID": "632"
              }
            ]
          }
        }
      },
      {
        "int": "369",
        "CerterDef": {
          "type": "fish",
          "certs": {
            "CertDef": [
              {
                "name": "Lobster",
                "certID": "533",
                "itemID": "373"
              },
              {
                "name": "Raw Lobster",
                "certID": "534",
                "itemID": "372"
              },
              {
                "name": "Swordfish",
                "certID": "535",
                "itemID": "370"
              },
              {
                "name": "Raw Swordfish",
                "certID": "536",
                "itemID": "369"
              },
              {
                "name": "Tuna",
                "certID": "1291",
                "itemID": "367"
              },
              {
                "name": "Raw Tuna",
                "certID": "1292",
                "itemID": "366"
              }
            ]
          }
        }
      },
      {
        "int": "370",
        "CerterDef": {
          "type": "fish",
          "certs": {
            "CertDef": [
              {
                "name": "Shark",
                "certID": "630",
                "itemID": "546"
              },
              {
                "name": "Raw Shark",
                "certID": "631",
                "itemID": "545"
              },
              {
                "name": "Bass",
                "certID": "628",
                "itemID": "555"
              },
              {
                "name": "Raw Bass",
                "certID": "629",
                "itemID": "554"
              }
            ]
          }
        }
      },
      {
        "int": "144",
        "CerterDef": {
          "type": "ore",
          "certs": {
            "CertDef": [
              {
                "name": "Iron",
                "certID": "517",
                "itemID": "151"
              },
              {
                "name": "Coal",
                "certID": "518",
                "itemID": "155"
              },
              {
                "name": "Mithril",
                "certID": "519",
                "itemID": "153"
              }
            ]
          }
        }
      },
      {
        "int": "794",
        "CerterDef": {
          "type": "flax",
          "certs": {
            "CertDef": [
              {
                "name": "Flax",
                "certID": "1293",
                "itemID": "675"
              },
              {
                "name": "Bow Strings",
                "certID": "1294",
                "itemID": "676"
              }
            ]
          }
        }
      },
      {
        "int": "267",
        "CerterDef": {
          "type": "fish",
          "certs": {
            "CertDef": [
              {
                "name": "Lobster",
                "certID": "533",
                "itemID": "373"
              },
              {
                "name": "Raw Lobster",
                "certID": "534",
                "itemID": "372"
              },
              {
                "name": "Swordfish",
                "certID": "535",
                "itemID": "370"
              },
              {
                "name": "Raw Swordfish",
                "certID": "536",
                "itemID": "369"
              },
              {
                "name": "Tuna",
                "certID": "1291",
                "itemID": "367"
              },
              {
                "name": "Raw Tuna",
                "certID": "1292",
                "itemID": "366"
              }
            ]
          }
        }
      },
      {
        "int": "795",
        "CerterDef": {
          "type": "herblaw supplies",
          "certs": {
            "CertDef": [
              {
                "name": "Empty Vial",
                "certID": "1297",
                "itemID": "465"
              },
              {
                "name": "Full Vial",
                "certID": "1298",
                "itemID": "464"
              },
              {
                "name": "Eye of Newt",
                "certID": "1299",
                "itemID": "270"
              },
              {
                "name": "Limpwurt Root",
                "certID": "1271",
                "itemID": "220"
              },
              {
                "name": "Snape Grass",
                "certID": "1311",
                "itemID": "469"
              },
              {
                "name": "White Berries",
                "certID": "1312",
                "itemID": "471"
              },
              {
                "name": "Red Spider Eggs",
                "certID": "1313",
                "itemID": "219"
              }
            ]
          }
        }
      },
      {
        "int": "231",
        "CerterDef": {
          "type": "ore",
          "certs": {
            "CertDef": [
              {
                "name": "Gold",
                "certID": "521",
                "itemID": "152"
              },
              {
                "name": "Silver",
                "certID": "520",
                "itemID": "383"
              }
            ]
          }
        }
      }
    ]
  }
}